Workbook
Name RMV: 'Parámetros'!$B$5
Name TasaAsigFam: 'Parámetros'!$B$6
Name TasaONP: 'Parámetros'!$B$7
Name TasaEsSalud: 'Parámetros'!$B$8
Name Recargo25: 'Parámetros'!$B$9
Name Recargo35: 'Parámetros'!$B$10
Name DiasMes: 'Parámetros'!$B$11
Name HorasDia: 'Parámetros'!$B$12
Name AFP_Nombres: 'Parámetros'!$A$17:$A$21
Name AFP_Fondo: 'Parámetros'!$B$17:$B$21
Name AFP_Comision: 'Parámetros'!$C$17:$C$21
Name AFP_Seguro: 'Parámetros'!$D$17:$D$21

Sheet Parámetros
A1: Parámetros de cálculo
A2: Los parámetros van en un solo lugar: ninguna fórmula lleva estos números escritos a mano.
A4: Parámetro | B4: Valor | C4: Nombre en fórmulas | D4: Fuente | E4: Fecha de consulta
A5: Remuneración mínima vital (RMV) | B5: 1230 | C5: RMV | D5: D.S. de la RMV, vigente desde el 1 de octubre de 2026 (dato del enunciado) | E5: 28/10/2026
A6: Asignación familiar (% de la RMV) | B6: 0.1 | C6: TasaAsigFam | D6: Ley 25129 | E6: 28/10/2026
A7: Aporte ONP | B7: 0.13 | C7: TasaONP | D7: D.L. 19990 | E7: 28/10/2026
A8: Aporte EsSalud (empleador) | B8: 0.09 | C8: TasaEsSalud | D8: Ley 26790 | E8: 28/10/2026
A9: Recargo horas extras 25% | B9: 1.25 | C9: Recargo25 | D9: Normas de jornada y sobretiempo (D.S. 007-2002-TR) | E9: 28/10/2026
A10: Recargo horas extras 35% | B10: 1.35 | C10: Recargo35 | D10: Normas de jornada y sobretiempo (D.S. 007-2002-TR) | E10: 28/10/2026
A11: Días del mes (convención) | B11: 30 | C11: DiasMes | D11: Enunciado: sueldo ÷ 30 | E11: 28/10/2026
A12: Horas por día (convención) | B12: 8 | C12: HorasDia | D12: Enunciado: valor hora = sueldo ÷ 30 ÷ 8 | E12: 28/10/2026
A15: Tasas de las AFP (se aplican sobre el total de remuneraciones)
A16: AFP | B16: Aporte al fondo | C16: Comisión sobre flujo | D16: Prima de seguro | E16: Fuente
A17: AFP Ejemplo | B17: 0.1 | C17: 0.016 | D17: 0.0135 | E17: Enunciado del laboratorio (solo para los casos de prueba)
A18: Habitat | B18: 0.1 | C18: 0.0147 | D18: 0.0137 | E18: SBS, comisiones y primas, mes de devengue 2026-10 (consultado el 28/10/2026)
A19: Integra | B19: 0.1 | C19: 0.0155 | D19: 0.0137 | E19: SBS, comisiones y primas, mes de devengue 2026-10 (consultado el 28/10/2026)
A20: Prima | B20: 0.1 | C20: 0.016 | D20: 0.0137 | E20: SBS, comisiones y primas, mes de devengue 2026-10 (consultado el 28/10/2026)
A21: Profuturo | B21: 0.1 | C21: 0.0169 | D21: 0.0137 | E21: SBS, comisiones y primas, mes de devengue 2026-10 (consultado el 28/10/2026)
A23: Leyenda: texto azul = dato que se puede cambiar · texto negro = fórmula · fondo amarillo = dato que se ingresa.

Sheet Boleta
A1: Boleta de ejemplo · cálculo con fórmulas visibles
A2: Cambia las celdas amarillas y la boleta se recalcula. Seleccione una celda negra para ver su fórmula.
A4: Dato de entrada | B4: Valor | C4: Validación
A5: Sueldo básico (S/) | B5: 3000 | C5: Mayor que cero
A6: Días laborados | B6: 30 | C6: Entre 1 y 30
A7: ¿Tiene hijos? (Sí / No) | B7: Sí | C7: Lista: Sí, No
A8: Sistema de pensiones (ONP / AFP) | B8: AFP | C8: Lista: ONP, AFP
A9: AFP (si eligió AFP) | B9: AFP Ejemplo | C9: Lista de la hoja Parámetros
A10: Horas extras al 25% | B10: 4 | C10: Mayor o igual a cero
A11: Horas extras al 35% | B11: 4 | C11: Mayor o igual a cero
A12: Adelantos (S/) | B12: 200 | C12: Mayor o igual a cero
A14: Estado de los datos | B14: =IF(OR(B5<=0,B6<1,B6>30,B6<>INT(B6),B10<0,B11<0,B12<0),"Datos no válidos: revisa sueldo, días (1 a 30), horas y adelantos","Datos válidos")
A16: Concepto | B16: Monto (S/) | C16: Fórmula en Excel | D16: En palabras
A18: REMUNERACIONES
A19: Sueldo computable | B19: =ROUND(B5/DiasMes*B6,2) | C19: =REDONDEAR(Sueldo/DiasMes*Días;2) | D19: Sueldo básico ÷ 30 × días laborados
A20: Asignación familiar | B20: =IF(B7="Sí",ROUND(RMV*TasaAsigFam,2),0) | C20: =SI(Hijos="Sí";REDONDEAR(RMV*10%;2);0) | D20: 10% de la RMV si tiene hijos; no depende de los días
A21: Valor hora (referencia) | B21: =B5/DiasMes/HorasDia | C21: =Sueldo/DiasMes/HorasDia | D21: Cuánto vale una hora normal (no se suma)
A22: Horas extras 25% | B22: =ROUND(B21*Recargo25*B10,2) | C22: =REDONDEAR(ValorHora*1.25*Horas25;2) | D22: Cada hora extra se paga 25% más cara
A23: Horas extras 35% | B23: =ROUND(B21*Recargo35*B11,2) | C23: =REDONDEAR(ValorHora*1.35*Horas35;2) | D23: Las siguientes horas extras se pagan 35% más caras
A24: Total remuneraciones | B24: =B19+B20+B22+B23 | C24: =Computable+Asignación+HE25+HE35 | D24: Todo lo que gana el trabajador en el mes (bruto)
A25: RETENCIONES / DESCUENTOS
A26: ONP | B26: =IF(B8="ONP",ROUND(B24*TasaONP,2),0) | C26: =SI(Sistema="ONP";REDONDEAR(TotalRem*13%;2);0) | D26: 13% del total si está en la ONP
A27: AFP fondo | B27: =IF(B8="AFP",ROUND(B24*INDEX(AFP_Fondo,MATCH(B9,AFP_Nombres,0)),2),0) | C27: =SI(Sistema="AFP";REDONDEAR(TotalRem*TasaFondo;2);0) | D27: Ahorro para su propia cuenta de jubilación
A28: AFP comisión | B28: =IF(B8="AFP",ROUND(B24*INDEX(AFP_Comision,MATCH(B9,AFP_Nombres,0)),2),0) | C28: =SI(Sistema="AFP";REDONDEAR(TotalRem*TasaComisión;2);0) | D28: Lo que cobra la AFP por administrar el fondo
A29: AFP seguro | B29: =IF(B8="AFP",ROUND(B24*INDEX(AFP_Seguro,MATCH(B9,AFP_Nombres,0)),2),0) | C29: =SI(Sistema="AFP";REDONDEAR(TotalRem*TasaSeguro;2);0) | D29: Seguro de invalidez, sobrevivencia y sepelio
A30: Adelantos | B30: =ROUND(B12,2) | C30: =REDONDEAR(Adelantos;2) | D30: Dinero que ya se le pagó antes; se resta tal cual
A31: Total descuentos | B31: =SUM(B26:B30) | C31: =SUMA(ONP:Adelantos) | D31: Pensión (ONP o AFP) + adelantos
A32: APORTACIONES DEL EMPLEADOR
A33: EsSalud (9%) | B33: =ROUND(B24*TasaEsSalud,2) | C33: =REDONDEAR(TotalRem*9%;2) | D33: Lo paga la empresa: NO se descuenta al trabajador
A34: NETO A PAGAR | B34: =B24-B31 | C34: =TotalRem-TotalDesc | D34: Lo que realmente llega al bolsillo
A35: Costo total para el empleador | B35: =B24+B33 | C35: =TotalRem+EsSalud | D35: Remuneraciones + EsSalud
A36: % del bruto que llega como neto | B36: =IF(B24=0,0,B34/B24) | C36: =Neto/TotalRem | D36: Qué parte del sueldo bruto recibe el trabajador

Sheet Casos
A1: Casos de prueba y control cruzado con la app
A2: Cada fila repite las fórmulas de la hoja Boleta. La columna 'Neto en la app' es lo que mostró la app en el simulador.
A4: Caso | B4: Sueldo | C4: Días | D4: Hijos | E4: Sistema | F4: AFP | G4: HE 25% (h) | H4: HE 35% (h) | I4: Adelantos | J4: Sueldo computable | K4: Asignación familiar | L4: HE 25% S/ | M4: HE 35% S/ | N4: Total remuneraciones | O4: ONP | P4: AFP fondo | Q4: AFP comisión | R4: AFP seguro | S4: Adelantos S/ | T4: Total descuentos | U4: NETO A PAGAR | V4: EsSalud | W4: Neto del enunciado | X4: Neto en la app | Y4: Diferencia Excel − app | Z4: ¿Coincide?
A5: Caso 1 | B5: 2500 | C5: 30 | D5: No | E5: ONP | F5: AFP Ejemplo | G5: 0 | H5: 0 | I5: 0 | J5: =ROUND(B5/DiasMes*C5,2) | K5: =IF(D5="Sí",ROUND(RMV*TasaAsigFam,2),0) | L5: =ROUND(B5/DiasMes/HorasDia*Recargo25*G5,2) | M5: =ROUND(B5/DiasMes/HorasDia*Recargo35*H5,2) | N5: =J5+K5+L5+M5 | O5: =IF(E5="ONP",ROUND(N5*TasaONP,2),0) | P5: =IF(E5="AFP",ROUND(N5*INDEX(AFP_Fondo,MATCH(F5,AFP_Nombres,0)),2),0) | Q5: =IF(E5="AFP",ROUND(N5*INDEX(AFP_Comision,MATCH(F5,AFP_Nombres,0)),2),0) | R5: =IF(E5="AFP",ROUND(N5*INDEX(AFP_Seguro,MATCH(F5,AFP_Nombres,0)),2),0) | S5: =ROUND(I5,2) | T5: =SUM(O5:S5) | U5: =N5-T5 | V5: =ROUND(N5*TasaEsSalud,2) | W5: 2175 | X5: 2175 | Y5: =ROUND(U5-X5,2) | Z5: =IF(ROUND(U5-X5,2)=0,"Sí, al centavo","NO: revisar")
A6: Caso 2 | B6: 1800 | C6: 27 | D6: Sí | E6: ONP | F6: AFP Ejemplo | G6: 0 | H6: 0 | I6: 0 | J6: =ROUND(B6/DiasMes*C6,2) | K6: =IF(D6="Sí",ROUND(RMV*TasaAsigFam,2),0) | L6: =ROUND(B6/DiasMes/HorasDia*Recargo25*G6,2) | M6: =ROUND(B6/DiasMes/HorasDia*Recargo35*H6,2) | N6: =J6+K6+L6+M6 | O6: =IF(E6="ONP",ROUND(N6*TasaONP,2),0) | P6: =IF(E6="AFP",ROUND(N6*INDEX(AFP_Fondo,MATCH(F6,AFP_Nombres,0)),2),0) | Q6: =IF(E6="AFP",ROUND(N6*INDEX(AFP_Comision,MATCH(F6,AFP_Nombres,0)),2),0) | R6: =IF(E6="AFP",ROUND(N6*INDEX(AFP_Seguro,MATCH(F6,AFP_Nombres,0)),2),0) | S6: =ROUND(I6,2) | T6: =SUM(O6:S6) | U6: =N6-T6 | V6: =ROUND(N6*TasaEsSalud,2) | W6: 1516.41 | X6: 1516.41 | Y6: =ROUND(U6-X6,2) | Z6: =IF(ROUND(U6-X6,2)=0,"Sí, al centavo","NO: revisar")
A7: Caso 3 | B7: 3000 | C7: 30 | D7: Sí | E7: AFP | F7: AFP Ejemplo | G7: 4 | H7: 4 | I7: 200 | J7: =ROUND(B7/DiasMes*C7,2) | K7: =IF(D7="Sí",ROUND(RMV*TasaAsigFam,2),0) | L7: =ROUND(B7/DiasMes/HorasDia*Recargo25*G7,2) | M7: =ROUND(B7/DiasMes/HorasDia*Recargo35*H7,2) | N7: =J7+K7+L7+M7 | O7: =IF(E7="ONP",ROUND(N7*TasaONP,2),0) | P7: =IF(E7="AFP",ROUND(N7*INDEX(AFP_Fondo,MATCH(F7,AFP_Nombres,0)),2),0) | Q7: =IF(E7="AFP",ROUND(N7*INDEX(AFP_Comision,MATCH(F7,AFP_Nombres,0)),2),0) | R7: =IF(E7="AFP",ROUND(N7*INDEX(AFP_Seguro,MATCH(F7,AFP_Nombres,0)),2),0) | S7: =ROUND(I7,2) | T7: =SUM(O7:S7) | U7: =N7-T7 | V7: =ROUND(N7*TasaEsSalud,2) | W7: 2631.73 | X7: 2631.73 | Y7: =ROUND(U7-X7,2) | Z7: =IF(ROUND(U7-X7,2)=0,"Sí, al centavo","NO: revisar")
A8: Caso 4 (lo revisa el docente) | B8: 4200 | C8: 24 | D8: Sí | E8: AFP | F8: AFP Ejemplo | G8: 2 | H8: 2 | I8: 100 | J8: =ROUND(B8/DiasMes*C8,2) | K8: =IF(D8="Sí",ROUND(RMV*TasaAsigFam,2),0) | L8: =ROUND(B8/DiasMes/HorasDia*Recargo25*G8,2) | M8: =ROUND(B8/DiasMes/HorasDia*Recargo35*H8,2) | N8: =J8+K8+L8+M8 | O8: =IF(E8="ONP",ROUND(N8*TasaONP,2),0) | P8: =IF(E8="AFP",ROUND(N8*INDEX(AFP_Fondo,MATCH(F8,AFP_Nombres,0)),2),0) | Q8: =IF(E8="AFP",ROUND(N8*INDEX(AFP_Comision,MATCH(F8,AFP_Nombres,0)),2),0) | R8: =IF(E8="AFP",ROUND(N8*INDEX(AFP_Seguro,MATCH(F8,AFP_Nombres,0)),2),0) | S8: =ROUND(I8,2) | T8: =SUM(O8:S8) | U8: =N8-T8 | V8: =ROUND(N8*TasaEsSalud,2) | W8: — | X8: 3011.17 | Y8: =ROUND(U8-X8,2) | Z8: =IF(ROUND(U8-X8,2)=0,"Sí, al centavo","NO: revisar")
A9: Caso propio: oferta real S/ 1,700 (Habitat) | B9: 1700 | C9: 30 | D9: No | E9: AFP | F9: Habitat | G9: 0 | H9: 0 | I9: 0 | J9: =ROUND(B9/DiasMes*C9,2) | K9: =IF(D9="Sí",ROUND(RMV*TasaAsigFam,2),0) | L9: =ROUND(B9/DiasMes/HorasDia*Recargo25*G9,2) | M9: =ROUND(B9/DiasMes/HorasDia*Recargo35*H9,2) | N9: =J9+K9+L9+M9 | O9: =IF(E9="ONP",ROUND(N9*TasaONP,2),0) | P9: =IF(E9="AFP",ROUND(N9*INDEX(AFP_Fondo,MATCH(F9,AFP_Nombres,0)),2),0) | Q9: =IF(E9="AFP",ROUND(N9*INDEX(AFP_Comision,MATCH(F9,AFP_Nombres,0)),2),0) | R9: =IF(E9="AFP",ROUND(N9*INDEX(AFP_Seguro,MATCH(F9,AFP_Nombres,0)),2),0) | S9: =ROUND(I9,2) | T9: =SUM(O9:S9) | U9: =N9-T9 | V9: =ROUND(N9*TasaEsSalud,2) | W9: — | X9: 1481.72 | Y9: =ROUND(U9-X9,2) | Z9: =IF(ROUND(U9-X9,2)=0,"Sí, al centavo","NO: revisar")
A10: Análisis 1: caso 3 con ONP | B10: 3000 | C10: 30 | D10: Sí | E10: ONP | F10: AFP Ejemplo | G10: 4 | H10: 4 | I10: 200 | J10: =ROUND(B10/DiasMes*C10,2) | K10: =IF(D10="Sí",ROUND(RMV*TasaAsigFam,2),0) | L10: =ROUND(B10/DiasMes/HorasDia*Recargo25*G10,2) | M10: =ROUND(B10/DiasMes/HorasDia*Recargo35*H10,2) | N10: =J10+K10+L10+M10 | O10: =IF(E10="ONP",ROUND(N10*TasaONP,2),0) | P10: =IF(E10="AFP",ROUND(N10*INDEX(AFP_Fondo,MATCH(F10,AFP_Nombres,0)),2),0) | Q10: =IF(E10="AFP",ROUND(N10*INDEX(AFP_Comision,MATCH(F10,AFP_Nombres,0)),2),0) | R10: =IF(E10="AFP",ROUND(N10*INDEX(AFP_Seguro,MATCH(F10,AFP_Nombres,0)),2),0) | S10: =ROUND(I10,2) | T10: =SUM(O10:S10) | U10: =N10-T10 | V10: =ROUND(N10*TasaEsSalud,2) | W10: — | X10: 2630.11 | Y10: =ROUND(U10-X10,2) | Z10: =IF(ROUND(U10-X10,2)=0,"Sí, al centavo","NO: revisar")
A11: Análisis 3: caso 2 con 30 días | B11: 1800 | C11: 30 | D11: Sí | E11: ONP | F11: AFP Ejemplo | G11: 0 | H11: 0 | I11: 0 | J11: =ROUND(B11/DiasMes*C11,2) | K11: =IF(D11="Sí",ROUND(RMV*TasaAsigFam,2),0) | L11: =ROUND(B11/DiasMes/HorasDia*Recargo25*G11,2) | M11: =ROUND(B11/DiasMes/HorasDia*Recargo35*H11,2) | N11: =J11+K11+L11+M11 | O11: =IF(E11="ONP",ROUND(N11*TasaONP,2),0) | P11: =IF(E11="AFP",ROUND(N11*INDEX(AFP_Fondo,MATCH(F11,AFP_Nombres,0)),2),0) | Q11: =IF(E11="AFP",ROUND(N11*INDEX(AFP_Comision,MATCH(F11,AFP_Nombres,0)),2),0) | R11: =IF(E11="AFP",ROUND(N11*INDEX(AFP_Seguro,MATCH(F11,AFP_Nombres,0)),2),0) | S11: =ROUND(I11,2) | T11: =SUM(O11:S11) | U11: =N11-T11 | V11: =ROUND(N11*TasaEsSalud,2) | W11: — | X11: 1673.01 | Y11: =ROUND(U11-X11,2) | Z11: =IF(ROUND(U11-X11,2)=0,"Sí, al centavo","NO: revisar")
A12: Caso propio con ONP | B12: 1700 | C12: 30 | D12: No | E12: ONP | F12: AFP Ejemplo | G12: 0 | H12: 0 | I12: 0 | J12: =ROUND(B12/DiasMes*C12,2) | K12: =IF(D12="Sí",ROUND(RMV*TasaAsigFam,2),0) | L12: =ROUND(B12/DiasMes/HorasDia*Recargo25*G12,2) | M12: =ROUND(B12/DiasMes/HorasDia*Recargo35*H12,2) | N12: =J12+K12+L12+M12 | O12: =IF(E12="ONP",ROUND(N12*TasaONP,2),0) | P12: =IF(E12="AFP",ROUND(N12*INDEX(AFP_Fondo,MATCH(F12,AFP_Nombres,0)),2),0) | Q12: =IF(E12="AFP",ROUND(N12*INDEX(AFP_Comision,MATCH(F12,AFP_Nombres,0)),2),0) | R12: =IF(E12="AFP",ROUND(N12*INDEX(AFP_Seguro,MATCH(F12,AFP_Nombres,0)),2),0) | S12: =ROUND(I12,2) | T12: =SUM(O12:S12) | U12: =N12-T12 | V12: =ROUND(N12*TasaEsSalud,2) | W12: — | X12: 1479 | Y12: =ROUND(U12-X12,2) | Z12: =IF(ROUND(U12-X12,2)=0,"Sí, al centavo","NO: revisar")
A14: Fuente del caso propio: oferta 'Asistente de TI - Desarrollo y Soporte de Sistemas', Computrabajo Perú, S/ 1,700.00 mensuales, consultada el 28/10/2026: https://pe.computrabajo.com/ofertas-de-trabajo/oferta-de-trabajo-de-asistente-de-ti-desarrollo-y-soporte-de-sistemas-puente-piedra-en-puente-piedra-70B2AA847863D68061373E686DCF3405
A15: La boleta del caso propio usa nombres ficticios (Empresa Ejemplo S.A.C. / Trabajador de ejemplo); solo el sueldo viene de la oferta real.

Sheet Explicación
A1: Explicación de cada fórmula (para alguien que no sabe contabilidad)
A2: Ejemplo numérico con el caso 3: sueldo S/ 3,000 · 30 días · con hijos · AFP Ejemplo · 4 h al 25% · 4 h al 35% · adelanto S/ 200
A4: Concepto | B4: Qué significa y cómo se calcula | C4: Ejemplo numérico (caso 3) | D4: Resultado (S/)
A5: Sueldo computable | B5: Es la parte del sueldo que corresponde a los días que trabajó. Se divide el sueldo entre 30 para saber cuánto vale un día y se multiplica por los días laborados. | C5: 3,000 ÷ 30 × 30 | D5: =Casos!J7
A6: Asignación familiar | B6: Si el trabajador tiene hijos, recibe un monto fijo igual al 10% de la RMV. No se reduce si faltó algunos días. | C6: 10% × 1,230 | D6: =Casos!K7
A7: Valor hora | B7: Cuánto vale una hora normal de trabajo: sueldo ÷ 30 días ÷ 8 horas. Solo se usa para calcular las horas extras. | C7: 3,000 ÷ 30 ÷ 8 = 12.50 | D7: =Casos!B7/DiasMes/HorasDia
A8: Horas extras al 25% | B8: Las horas extra se pagan más caras que las normales: las primeras con 25% de recargo (valor hora × 1.25). | C8: 12.50 × 1.25 × 4 | D8: =Casos!L7
A9: Horas extras al 35% | B9: Las siguientes horas extra tienen 35% de recargo (valor hora × 1.35). | C9: 12.50 × 1.35 × 4 | D9: =Casos!M7
A10: Total remuneraciones | B10: Todo lo que gana en el mes antes de descuentos (sueldo bruto del mes). | C10: 3,000 + 123 + 62.50 + 67.50 | D10: =Casos!N7
A11: ONP | B11: Si está en la ONP (sistema del Estado), se le descuenta el 13% del total para su pensión. | C11: No aplica en el caso 3 (está en AFP) | D11: =Casos!O7
A12: AFP fondo | B12: Si está en una AFP, el 10% va a su propia cuenta de ahorro para la jubilación. | C12: 3,253 × 10% | D12: =Casos!P7
A13: AFP comisión | B13: Lo que cobra la AFP por administrar ese dinero. | C13: 3,253 × 1.60% = 52.048 → 52.05 | D13: =Casos!Q7
A14: AFP seguro | B14: Prima del seguro de invalidez, sobrevivencia y gastos de sepelio. | C14: 3,253 × 1.35% = 43.9155 → 43.92 | D14: =Casos!R7
A15: Adelantos | B15: Dinero que la empresa ya le pagó antes en el mes; se resta tal cual. | C15: 200.00 | D15: =Casos!S7
A16: Total descuentos | B16: Pensión (ONP o AFP) más adelantos. | C16: 325.30 + 52.05 + 43.92 + 200 | D16: =Casos!T7
A17: Neto a pagar | B17: Lo que de verdad recibe el trabajador: total de remuneraciones menos total de descuentos. | C17: 3,253.00 − 621.27 | D17: =Casos!U7
A18: EsSalud | B18: Seguro de salud que paga la empresa: 9% del total de remuneraciones. NO se le descuenta al trabajador. | C18: 3,253 × 9% | D18: =Casos!V7
A19: Redondeo | B19: Cada concepto se redondea a 2 decimales (REDONDEAR) y recién después se suman. Por eso 52.048 queda en 52.05. | C19: REDONDEAR(52.048; 2) | D19: =ROUND(52.048,2)
A22: Preguntas de análisis
A23: Pregunta | B23: Respuesta | C23: Cálculo | D23: Valor
A24: 1. ONP o AFP (caso 3) | B24: Con AFP Ejemplo el neto es S/ 2,631.73 y con ONP S/ 2,630.11: este mes la AFP deja S/ 1.62 más. No basta comparar porcentajes porque no son lo mismo: el 10% del fondo AFP se ahorra en una cuenta personal que gana rentabilidad, mientras que la ONP es un fondo común que paga una pensión fija si se cumplen 20 años de aportes. Además la comisión y el seguro cambian según la AFP. Hay que pensar en la pensión futura, no solo en el neto de este mes. | C24: Neto AFP − Neto ONP | D24: =Casos!U7-Casos!U10
A25: 2. Costo real para la empresa (caso 3) | B25: El trabajador le cuesta a la empresa S/ 3,545.77 (3,253.00 de remuneraciones + 292.77 de EsSalud). De ese costo, el 74.22% llega al trabajador como neto (S/ 2,631.73). | C25: Neto ÷ (Total rem. + EsSalud) | D25: =Casos!U7/(Casos!N7+Casos!V7)
A26: 3. Días laborados (caso 2) | B26: Con 30 días el neto sería S/ 1,673.01 en vez de S/ 1,516.41: S/ 156.60 más. El bruto sube S/ 180.00 (1,923 − 1,743). La diferencia en el neto es menor porque de esos S/ 180 también se descuenta el 13% de ONP (180 × 0.87 = 156.60). La asignación familiar no cambia porque no se prorratea por días. | C26: Neto 30 días − Neto 27 días | D26: =Casos!U11-Casos!U6
A27: 4. Horas extras (caso 3) | B27: Las horas extras suman S/ 130.00 (62.50 + 67.50), que es el 4.00% del total de remuneraciones (3,253.00). | C27: (HE25 + HE35) ÷ Total rem. | D27: =(Casos!L7+Casos!M7)/Casos!N7
A28: 5. Con datos reales | B28: Oferta real de Computrabajo (Asistente de TI, S/ 1,700.00, consultada el 28/10/2026). Con AFP Habitat (tasas SBS octubre 2026), sin hijos y mes completo: descuentos S/ 218.28 y neto S/ 1,481.72, es decir llega el 87.16% del sueldo bruto. Con ONP el neto sería S/ 1,479.00 (87.00%). Comparar con dos compañeros: completar abajo. | C28: Neto ÷ Total rem. | D28: =Casos!U9/Casos!N9
A30: Comparación con compañeros (pregunta 5)
A31: Alumno | B31: Sueldo bruto (S/) | C31: Neto (S/) | D31: % que llega
A32: Harold Salvador Zarate | B32: =Casos!N9 | C32: =Casos!U9 | D32: =IF(B32="","",C32/B32)
A33: Compañero 1 | D33: =IF(B33="","",C33/B33)
A34: Compañero 2 | D34: =IF(B34="","",C34/B34)
A37: Tabla de fuentes
A38: Dato | B38: Valor | C38: Fuente | D38: Fecha de consulta
A39: RMV | B39: S/ 1,230.00 | C39: D.S. de la RMV, vigente desde el 1 de octubre de 2026 (enunciado del laboratorio) | D39: 28/10/2026
A40: Asignación familiar | B40: 10% de la RMV = S/ 123.00 | C40: Ley 25129 | D40: 28/10/2026
A41: ONP | B41: 13% | C41: D.L. 19990 | D41: 28/10/2026
A42: EsSalud | B42: 9% | C42: Ley 26790 | D42: 28/10/2026
A43: Horas extras | B43: 25% y 35% de recargo | C43: D.S. 007-2002-TR (jornada de trabajo, horario y sobretiempo) | D43: 28/10/2026
A44: AFP Ejemplo | B44: Fondo 10% · comisión 1.60% · seguro 1.35% | C44: Enunciado del laboratorio (valores de prueba) | D44: 28/10/2026
A45: Tasas AFP reales | B45: Fondo 10% · comisión Habitat 1.47%, Integra 1.55%, Prima 1.60%, Profuturo 1.69% · seguro 1.37% | C45: SBS, comisiones y primas de seguro, mes de devengue 2026-10: https://www.sbs.gob.pe/app/spp/empleadores/comisiones_spp/Paginas/comision_prima.aspx | D45: 28/10/2026
A46: Sueldo real (caso propio) | B46: S/ 1,700.00 mensuales | C46: Computrabajo Perú, oferta 'Asistente de TI - Desarrollo y Soporte de Sistemas': https://pe.computrabajo.com/ofertas-de-trabajo/oferta-de-trabajo-de-asistente-de-ti-desarrollo-y-soporte-de-sistemas-puente-piedra-en-puente-piedra-70B2AA847863D68061373E686DCF3405 | D46: 28/10/2026
